core.py
nano_eval.py
nano_eval-0.2.5.dist-info/licenses/LICENSE
tasks/__init__.py
tasks/chartqa.py
tasks/gsm8k.py
nano_eval-0.2.5.dist-info/METADATA
nano_eval-0.2.5.dist-info/WHEEL
nano_eval-0.2.5.dist-info/entry_points.txt
nano_eval-0.2.5.dist-info/top_level.txt
nano_eval-0.2.5.dist-info/RECORD
