Metadata-Version: 2.4
Name: nano-eval
Version: 0.2.5
Summary: Nano Eval - A minimal tool for verifying VLMs/LLMs across frameworks
Author-email: Thomas Børstad <tboerstad@users.noreply.github.com>
License-Expression: MIT
Project-URL: Homepage, https://github.com/tboerstad/nano-eval
Project-URL: Repository, https://github.com/tboerstad/nano-eval
Project-URL: Issues, https://github.com/tboerstad/nano-eval/issues
Keywords: llm,evaluation,benchmark,openai,api,vllm,tgi
Classifier: Development Status :: 4 - Beta
Classifier: Programming Language :: Python :: 3
Classifier: Operating System :: OS Independent
Classifier: Topic :: Scientific/Engineering :: Artificial Intelligence
Requires-Python: >=3.10
License-File: LICENSE
Requires-Dist: click>=8.0.0
Requires-Dist: datasets>=2.0.0
Requires-Dist: httpx>=0.23.0
Requires-Dist: pillow>=9.0.0
Requires-Dist: tqdm>=4.62.0
Requires-Dist: typing-extensions>=4.0.0
Requires-Dist: multiprocess<=0.70.17
Provides-Extra: dev
Requires-Dist: pytest>=7.0.0; extra == "dev"
Requires-Dist: pytest-cov>=4.0.0; extra == "dev"
Requires-Dist: ruff>=0.1.0; extra == "dev"
Requires-Dist: prek>=0.2.0; extra == "dev"
Requires-Dist: respx>=0.20.0; extra == "dev"
Requires-Dist: ty>=0.0.1; extra == "dev"
Dynamic: license-file
